ojuara.py
grande_ojuara_pypi-1.0.dist-info/METADATA
grande_ojuara_pypi-1.0.dist-info/WHEEL
grande_ojuara_pypi-1.0.dist-info/top_level.txt
grande_ojuara_pypi-1.0.dist-info/RECORD
