Metadata-Version: 2.1
Name: grande-ojuara-pypi
Version: 1.0
Summary: Brincando com distribuição python
Home-page: UNKNOWN
Author: Daniel, William, Udglylania, Ariany e Luan
Author-email: ojuara@araujo.com
License: UNKNOWN
Platform: UNKNOWN
